fuisce/_version.py
fuisce/database/__init__.py
fuisce/database/interface.py
fuisce/testing/__init__.py
fuisce/testing/config.py
fuisce/testing/manager.py
fuisce-1.0.2.dist-info/METADATA
fuisce-1.0.2.dist-info/WHEEL
fuisce-1.0.2.dist-info/entry_points.txt
fuisce-1.0.2.dist-info/licenses/COPYING
fuisce-1.0.2.dist-info/licenses/LICENSE
fuisce-1.0.2.dist-info/RECORD
