Metadata-Version: 2.1
Name: fuisce
Version: 1.0.2
Summary: Database management and testing for SQLAlchemy-based Flask apps.
Project-URL: Download, https://pypi.org/project/fuisce
Project-URL: Homepage, https://github.com/mitchnegus/fuisce
Project-URL: Repository, https://github.com/mitchnegus/fuisce
Project-URL: Changelog, https://github.com/mitchnegus/fuisce/blob/main/CHANGELOG.md
Author-email: Mitch Negus <mitchnegus57@gmail.com>
License: GNU GPLv3
License-File: COPYING
License-File: LICENSE
Classifier: Development Status :: 3 - Alpha
Classifier: Framework :: Flask
Classifier: Framework :: Pytest
Classifier: License :: OSI Approved :: GNU General Public License v3 (GPLv3)
Classifier: Natural Language :: English
Classifier: Operating System :: OS Independent
Classifier: Programming Language :: Python
Requires-Python: <3.11,>=3.9
Requires-Dist: flask>=2.2.2
Requires-Dist: sqlalchemy-views>=0.3.2
Requires-Dist: sqlalchemy>=2.0.0
